Metadata-Version: 1.0
Name: dist-probabilty
Version: 1.1
Summary: Gaussian and Binomail distributions
Home-page: UNKNOWN
Author: Carter Wright
Author-email: random@gmail.com
License: UNKNOWN
Platform: UNKNOWN
